hydra_buddies/__init__.py
hydra_buddies/buddies.py
hydra_buddies/cli.py
hydra_buddies/templates/hydra_conf/cookiecutter.json
hydra_buddies/templates/hydra_conf/{{cookiecutter.project_name}}/.hydra-conf/api/default.yaml
hydra_buddies/templates/hydra_conf/{{cookiecutter.project_name}}/.hydra-conf/api/dev.yaml
hydra_buddies/templates/hydra_conf/{{cookiecutter.project_name}}/.hydra-conf/api/prod.yaml
hydra_buddies/templates/hydra_conf/{{cookiecutter.project_name}}/.hydra-conf/config.yaml
hydra_buddies/templates/hydra_conf/{{cookiecutter.project_name}}/.hydra-conf/database/default.yaml
hydra_buddies/templates/hydra_conf/{{cookiecutter.project_name}}/.hydra-conf/database/dev.yaml
hydra_buddies/templates/hydra_conf/{{cookiecutter.project_name}}/.hydra-conf/database/prod.yaml
hydra_buddies/templates/hydra_conf/{{cookiecutter.project_name}}/.hydra-conf/logging/default.yaml
hydra_buddies/templates/hydra_conf/{{cookiecutter.project_name}}/.hydra-conf/logging/dev.yaml
hydra_buddies/templates/hydra_conf/{{cookiecutter.project_name}}/.hydra-conf/logging/prod.yaml
hydra_buddies/templates/hydra_conf/{{cookiecutter.project_name}}/.hydra-conf/secrets/keys.yaml
hydra_buddies/templates/hydra_conf/{{cookiecutter.project_name}}/.hydra-conf/secrets/login.yaml
hydra_buddies/test.py
hydra_buddies-0.1.7.dist-info/LICENSE
hydra_buddies-0.1.7.dist-info/METADATA
hydra_buddies-0.1.7.dist-info/WHEEL
hydra_buddies-0.1.7.dist-info/entry_points.txt
hydra_buddies-0.1.7.dist-info/RECORD
