Metadata-Version: 2.1
Name: hydra-buddies
Version: 0.1.7
Summary: Un gestionnaire de configuration basé sur Hydra
Home-page: https://github.com/DemiurgeGalaxie/hydra-buddy
License: MIT
Keywords: hydra,configuration,omegaconf
Author: MChrys
Author-email: chrys.beltran@outlook.fr
Requires-Python: >=3.12,<4.0
Classifier: License :: OSI Approved :: MIT License
Classifier: Programming Language :: Python :: 3
Classifier: Programming Language :: Python :: 3.12
Requires-Dist: click (>=8.1.7,<9.0.0)
Requires-Dist: cookiecutter (>=2.5.0,<3.0.0)
Requires-Dist: hydra-core (>=1.3.2,<2.0.0)
Requires-Dist: ipykernel (>=6.29.5,<7.0.0)
Requires-Dist: omegaconf (>=2.3.0,<3.0.0)
Requires-Dist: tomlkit (>=0.13.2,<0.14.0)
Project-URL: Repository, https://github.com/DemiurgeGalaxie/hydra-buddy
